openmldb_provider/__init__.py
openmldb_provider/hooks/__init__.py
openmldb_provider/hooks/openmldb_hook.py
openmldb_provider/operators/__init__.py
openmldb_provider/operators/openmldb_operator.py
airflow_provider_openmldb-0.0.1.dist-info/METADATA
airflow_provider_openmldb-0.0.1.dist-info/WHEEL
airflow_provider_openmldb-0.0.1.dist-info/entry_points.txt
airflow_provider_openmldb-0.0.1.dist-info/top_level.txt
airflow_provider_openmldb-0.0.1.dist-info/RECORD
