Metadata-Version: 2.1
Name: airflow-provider-openmldb
Version: 0.0.1
Summary: A openmldb provider package built by 4paradigm.
Home-page: https://github.com/4paradigm/OpenMLDB
Author: Huang Wei
Author-email: huangwei@apache.org
License: copyright 4paradigm.com
Classifier: Framework :: Apache Airflow
Classifier: Framework :: Apache Airflow :: Provider
Requires-Python: ~=3.7
Requires-Dist: apache-airflow (>=2.0)
